[
	{
		"id": 1,
		"name": "Germinal 1",
		"desc": "description germinal 1",
		"price": 10
	},
	{
		"id": 2,
		"name": "Germinal 2",
		"desc": "description germinal 2",
		"price": 20
	},
	{
		"id": 3,
		"name": "Germinal 3",
		"desc": "description germinal 3",
		"price": 30
	},
	{
		"id": 4,
		"name": "Germinal 4",
		"desc": "description germinal 4",
		"price": 40
	},
	{
		"id": 5,
		"name": "Germinal 5",
		"desc": "description germinal 5",
		"price": 50
	},
	{
		"id": 6,
		"name": "Germinal 6",
		"desc": "description germinal 6",
		"price": 60
	},
	{
		"id": 7,
		"name": "Germinal 7",
		"desc": "description germinal 7",
		"price": 70
	},
	{
		"id": 8,
		"name": "Germinal 8",
		"desc": "description germinal 8",
		"price": 80
	},
	{
		"id": 9,
		"name": "Germinal 9",
		"desc": "description germinal 9",
		"price": 90
	},
	{
		"id": 10,
		"name": "Germinal 10",
		"desc": "description germinal 10",
		"price": 100
	},
	{
		"id": 11,
		"name": "Germinal 11",
		"desc": "description germinal 11",
		"price": 110
	}
]